django_aws_api_gateway_websockets/__init__.py
django_aws_api_gateway_websockets/admin.py
django_aws_api_gateway_websockets/apps.py
django_aws_api_gateway_websockets/models.py
django_aws_api_gateway_websockets/py.typed
django_aws_api_gateway_websockets/views.py
django_aws_api_gateway_websockets/management/__init__.py
django_aws_api_gateway_websockets/management/commands/__init__.py
django_aws_api_gateway_websockets/management/commands/clearWebSocketSessions.py
django_aws_api_gateway_websockets/management/commands/createApiGateway.py
django_aws_api_gateway_websockets/management/commands/createCustomDomain.py
django_aws_api_gateway_websockets/migrations/0001_initial.py
django_aws_api_gateway_websockets/migrations/0002_rename_author_websocketsession_user.py
django_aws_api_gateway_websockets/migrations/0003_auto_20220706_1018.py
django_aws_api_gateway_websockets/migrations/0004_auto_20221208_1227.py
django_aws_api_gateway_websockets/migrations/0005_apigatewayadditionalroute_deployed.py
django_aws_api_gateway_websockets/migrations/0006_auto_20221215_0847.py
django_aws_api_gateway_websockets/migrations/__init__.py
django_aws_api_gateway_websockets-1.0.13.dist-info/LICENSE
django_aws_api_gateway_websockets-1.0.13.dist-info/METADATA
django_aws_api_gateway_websockets-1.0.13.dist-info/WHEEL
django_aws_api_gateway_websockets-1.0.13.dist-info/top_level.txt
django_aws_api_gateway_websockets-1.0.13.dist-info/RECORD
