Metadata-Version: 2.1
Name: django-aws-api-gateway-websockets
Version: 1.0.13
Summary: Created to allow Django projects to be used as a HTTP backend for AWS API Gateway websockets
Home-page: https://github.com/StevenMapes/django-aws-api-gateway-websockets
Author: Steven Mapes
Author-email: Steven Mapes <steve@stevenmapes.com>
License: MIT
Project-URL: Homepage, https://github.com/StevenMapes/django-aws-api-gateway-websockets
Project-URL: Change log, https://github.com/StevenMapes/django-aws-api-gateway-websockets/blob/main/CHANGELOG.md
Project-URL: Twitter, https://twitter.com/stevenamapes
Keywords: Django,WebSockets,AWS,API Gateway,Amazon WebServices
Classifier: Development Status :: 5 - Production/Stable
Classifier: Framework :: Django
Classifier: Framework :: Django :: 3.2
Classifier: Framework :: Django :: 4.0
Classifier: Framework :: Django :: 4.1
Classifier: Framework :: Django :: 4.2
Classifier: Framework :: Django :: 5.0
Classifier: Intended Audience :: Developers
Classifier: Natural Language :: English
Classifier: Operating System :: OS Independent
Classifier: Programming Language :: Python :: 3 :: Only
Classifier: Programming Language :: Python :: 3.8
Classifier: Programming Language :: Python :: 3.9
Classifier: Programming Language :: Python :: 3.10
Classifier: Programming Language :: Python :: 3.11
Classifier: Programming Language :: Python :: 3.12
Requires-Python: >=3.8
License-File: LICENSE
Requires-Dist: Django >=3.2.0
